src/hdl/crc/crc_8.v

 /*
    Module  : CRC_8
    Version : 1.0
    Author  : Herzog Cyril
    Date    : 11.08.2024
    
*/

`ifndef _CRC_8_V_
`define _CRC_8_V_

module crc_8 #(
    parameter POLY  = 8'b00000111, // polynominal x^8 + x^2 + x^1 + 1 
    parameter INIT  = 8'b11111111  // initial value
)(
    input wire i_clk, i_arst_n,
    input wire i_init, i_calc,
    input wire [7:0] i_data,
    output wire [7:0] o_crc
);


    // function for calculate crc-8
    function [7:0] crc_calc(input reg [7:0] i_data, poly);
        reg[7:0] temp;
        integer i;
        begin
            temp = i_data;
            for (i=0; i < 8; i = i + 1) begin
                if (temp[7] == 1'b1)
                    temp = (temp << 1) ^ poly;
                else
                    temp = (temp << 1);
            end
            crc_calc = temp; // calculated crc value
        end
    endfunction         

    // ****************************************************************************
    // generate crc-lut
    wire [7:0] crc_lut [255:0];

    generate
        genvar i;
        for (i = 0; i < 256; i = i + 1) begin
            assign crc_lut[i] = crc_calc(i, POLY);
        end
    endgenerate

    // *****************************************************************************
    // crc-register output logic

    reg [7:0] r_crc;
    wire [7:0] ri_crc;

    always @ (posedge i_clk, negedge i_arst_n)
        if (~i_arst_n)
            r_crc <= INIT;
        else
            r_crc <= ri_crc;


    // next crc - logic
    assign ri_crc = (i_init) ? INIT : // init crc
                    (i_calc) ? crc_lut[(r_crc^i_data)] : // calc next crc
                               r_crc; // no change 

    // crc output
    assign o_crc = r_crc;

endmodule

`endif /* CRC_8 */

src/hdl/crc/sim/crc_tb.v
 /*
    Module  : CRC_TB
    Version : 1.0
    Author  : Herzog Cyril
    Date    : 20.12.2023
    
*/



`timescale 1ns/1ns


module crc_tb;

    reg sim_clk;
    reg sim_arst_n;
    reg sim_init, sim_calc;
    reg [7:0] sim_data_in;


    integer k;
    reg [7:0] sim_frame [7:0]; 

    initial begin
        $dumpfile("sim/icarus/crc.vcd");
        $dumpvars(0, crc_tb);
    end


    

    initial begin
        sim_clk = 1'b1;
            forever
                #5 sim_clk = ~sim_clk;
        end

    initial 
    begin
    #0      sim_arst_n    = 1'b0;
            sim_data_in   = 8'b0;
            k             = 0;
            sim_init      = 1'b1;
            sim_calc      = 1'b0; 
    #100    sim_arst_n    = 1'b1;
    #20     sim_init      = 1'b0;
            @(posedge sim_clk) sim_calc = 1'b1;
            while (k < 7) begin
                sim_frame[k] = $random;
                @(posedge sim_clk) sim_data_in = sim_frame[k];
                k = k + 1;
            end
            @(posedge sim_clk) sim_calc = 1'b0;
            sim_frame[7] = dut_crc_8.o_crc;
    #200    k = 0;
            @(posedge sim_clk) sim_init = 1'b1;
            @(posedge sim_clk) sim_init = 1'b0; 
            while (k < 8) begin
                @(posedge sim_clk) sim_data_in = sim_frame[k]; sim_calc = 1'b1;
                k = k + 1;
            end
            @(posedge sim_clk) sim_calc = 1'b0;
            @(posedge sim_clk) // next cycle
            if (dut_crc_8.o_crc === 0)
                $display("Test passed: crc = %h", dut_crc_8.o_crc);
            else
                $display("Test failed: crc = %h", dut_crc_8.o_crc);


    #1000  $finish;
    end

    crc_8 #(
        .POLY     (8'b00000111),
        .INIT     (8'b00000000)
    ) dut_crc_8 (
        .i_clk    (sim_clk),
        .i_arst_n (sim_arst_n),
        .i_init   (sim_init),
        .i_calc   (sim_calc),
        .i_data   (sim_data_in),
        .o_crc    ()
    );


    endmodule

src/hdl/crc/sim/icarus/crc.vcd
$date
	Fri Jan 19 13:45:04 2024
$end
$version
	Icarus Verilog
$end
$timescale
	1ns
$end
$scope module crc_tb $end
$var reg 1 ! sim_arst_n $end
$var reg 1 " sim_calc $end
$var reg 1 # sim_clk $end
$var reg 8 $ sim_data_in [7:0] $end
$var reg 1 % sim_init $end
$var integer 32 & k [31:0] $end
$scope module dut_crc_8 $end
$var wire 1 ! i_arst_n $end
$var wire 1 " i_calc $end
$var wire 1 # i_clk $end
$var wire 8 ' i_data [7:0] $end
$var wire 1 % i_init $end
$var wire 8 ( o_crc [7:0] $end
$var wire 8 ) ri_crc [7:0] $end
$var parameter 8 * INIT $end
$var parameter 8 + POLY $end
$var reg 8 , r_crc [7:0] $end
$scope function crc_calc $end
$var reg 8 - i_data [7:0] $end
$var reg 8 . poly [7:0] $end
$var reg 8 / temp [7:0] $end
$var integer 32 0 i [31:0] $end
$upscope $end
$scope begin genblk1[0] $end
$var parameter 2 1 i $end
$upscope $end
$scope begin genblk1[1] $end
$var parameter 2 2 i $end
$upscope $end
$scope begin genblk1[2] $end
$var parameter 3 3 i $end
$upscope $end
$scope begin genblk1[3] $end
$var parameter 3 4 i $end
$upscope $end
$scope begin genblk1[4] $end
$var parameter 4 5 i $end
$upscope $end
$scope begin genblk1[5] $end
$var parameter 4 6 i $end
$upscope $end
$scope begin genblk1[6] $end
$var parameter 4 7 i $end
$upscope $end
$scope begin genblk1[7] $end
$var parameter 4 8 i $end
$upscope $end
$scope begin genblk1[8] $end
$var parameter 5 9 i $end
$upscope $end
$scope begin genblk1[9] $end
$var parameter 5 : i $end
$upscope $end
$scope begin genblk1[10] $end
$var parameter 5 ; i $end
$upscope $end
$scope begin genblk1[11] $end
$var parameter 5 < i $end
$upscope $end
$scope begin genblk1[12] $end
$var parameter 5 = i $end
$upscope $end
$scope begin genblk1[13] $end
$var parameter 5 > i $end
$upscope $end
$scope begin genblk1[14] $end
$var parameter 5 ? i $end
$upscope $end
$scope begin genblk1[15] $end
$var parameter 5 @ i $end
$upscope $end
$scope begin genblk1[16] $end
$var parameter 6 A i $end
$upscope $end
$scope begin genblk1[17] $end
$var parameter 6 B i $end
$upscope $end
$scope begin genblk1[18] $end
$var parameter 6 C i $end
$upscope $end
$scope begin genblk1[19] $end
$var parameter 6 D i $end
$upscope $end
$scope begin genblk1[20] $end
$var parameter 6 E i $end
$upscope $end
$scope begin genblk1[21] $end
$var parameter 6 F i $end
$upscope $end
$scope begin genblk1[22] $end
$var parameter 6 G i $end
$upscope $end
$scope begin genblk1[23] $end
$var parameter 6 H i $end
$upscope $end
$scope begin genblk1[24] $end
$var parameter 6 I i $end
$upscope $end
$scope begin genblk1[25] $end
$var parameter 6 J i $end
$upscope $end
$scope begin genblk1[26] $end
$var parameter 6 K i $end
$upscope $end
$scope begin genblk1[27] $end
$var parameter 6 L i $end
$upscope $end
$scope begin genblk1[28] $end
$var parameter 6 M i $end
$upscope $end
$scope begin genblk1[29] $end
$var parameter 6 N i $end
$upscope $end
$scope begin genblk1[30] $end
$var parameter 6 O i $end
$upscope $end
$scope begin genblk1[31] $end
$var parameter 6 P i $end
$upscope $end
$scope begin genblk1[32] $end
$var parameter 7 Q i $end
$upscope $end
$scope begin genblk1[33] $end
$var parameter 7 R i $end
$upscope $end
$scope begin genblk1[34] $end
$var parameter 7 S i $end
$upscope $end
$scope begin genblk1[35] $end
$var parameter 7 T i $end
$upscope $end
$scope begin genblk1[36] $end
$var parameter 7 U i $end
$upscope $end
$scope begin genblk1[37] $end
$var parameter 7 V i $end
$upscope $end
$scope begin genblk1[38] $end
$var parameter 7 W i $end
$upscope $end
$scope begin genblk1[39] $end
$var parameter 7 X i $end
$upscope $end
$scope begin genblk1[40] $end
$var parameter 7 Y i $end
$upscope $end
$scope begin genblk1[41] $end
$var parameter 7 Z i $end
$upscope $end
$scope begin genblk1[42] $end
$var parameter 7 [ i $end
$upscope $end
$scope begin genblk1[43] $end
$var parameter 7 \ i $end
$upscope $end
$scope begin genblk1[44] $end
$var parameter 7 ] i $end
$upscope $end
$scope begin genblk1[45] $end
$var parameter 7 ^ i $end
$upscope $end
$scope begin genblk1[46] $end
$var parameter 7 _ i $end
$upscope $end
$scope begin genblk1[47] $end
$var parameter 7 ` i $end
$upscope $end
$scope begin genblk1[48] $end
$var parameter 7 a i $end
$upscope $end
$scope begin genblk1[49] $end
$var parameter 7 b i $end
$upscope $end
$scope begin genblk1[50] $end
$var parameter 7 c i $end
$upscope $end
$scope begin genblk1[51] $end
$var parameter 7 d i $end
$upscope $end
$scope begin genblk1[52] $end
$var parameter 7 e i $end
$upscope $end
$scope begin genblk1[53] $end
$var parameter 7 f i $end
$upscope $end
$scope begin genblk1[54] $end
$var parameter 7 g i $end
$upscope $end
$scope begin genblk1[55] $end
$var parameter 7 h i $end
$upscope $end
$scope begin genblk1[56] $end
$var parameter 7 i i $end
$upscope $end
$scope begin genblk1[57] $end
$var parameter 7 j i $end
$upscope $end
$scope begin genblk1[58] $end
$var parameter 7 k i $end
$upscope $end
$scope begin genblk1[59] $end
$var parameter 7 l i $end
$upscope $end
$scope begin genblk1[60] $end
$var parameter 7 m i $end
$upscope $end
$scope begin genblk1[61] $end
$var parameter 7 n i $end
$upscope $end
$scope begin genblk1[62] $end
$var parameter 7 o i $end
$upscope $end
$scope begin genblk1[63] $end
$var parameter 7 p i $end
$upscope $end
$scope begin genblk1[64] $end
$var parameter 8 q i $end
$upscope $end
$scope begin genblk1[65] $end
$var parameter 8 r i $end
$upscope $end
$scope begin genblk1[66] $end
$var parameter 8 s i $end
$upscope $end
$scope begin genblk1[67] $end
$var parameter 8 t i $end
$upscope $end
$scope begin genblk1[68] $end
$var parameter 8 u i $end
$upscope $end
$scope begin genblk1[69] $end
$var parameter 8 v i $end
$upscope $end
$scope begin genblk1[70] $end
$var parameter 8 w i $end
$upscope $end
$scope begin genblk1[71] $end
$var parameter 8 x i $end
$upscope $end
$scope begin genblk1[72] $end
$var parameter 8 y i $end
$upscope $end
$scope begin genblk1[73] $end
$var parameter 8 z i $end
$upscope $end
$scope begin genblk1[74] $end
$var parameter 8 { i $end
$upscope $end
$scope begin genblk1[75] $end
$var parameter 8 | i $end
$upscope $end
$scope begin genblk1[76] $end
$var parameter 8 } i $end
$upscope $end
$scope begin genblk1[77] $end
$var parameter 8 ~ i $end
$upscope $end
$scope begin genblk1[78] $end
$var parameter 8 !" i $end
$upscope $end
$scope begin genblk1[79] $end
$var parameter 8 "" i $end
$upscope $end
$scope begin genblk1[80] $end
$var parameter 8 #" i $end
$upscope $end
$scope begin genblk1[81] $end
$var parameter 8 $" i $end
$upscope $end
$scope begin genblk1[82] $end
$var parameter 8 %" i $end
$upscope $end
$scope begin genblk1[83] $end
$var parameter 8 &" i $end
$upscope $end
$scope begin genblk1[84] $end
$var parameter 8 '" i $end
$upscope $end
$scope begin genblk1[85] $end
$var parameter 8 (" i $end
$upscope $end
$scope begin genblk1[86] $end
$var parameter 8 )" i $end
$upscope $end
$scope begin genblk1[87] $end
$var parameter 8 *" i $end
$upscope $end
$scope begin genblk1[88] $end
$var parameter 8 +" i $end
$upscope $end
$scope begin genblk1[89] $end
$var parameter 8 ," i $end
$upscope $end
$scope begin genblk1[90] $end
$var parameter 8 -" i $end
$upscope $end
$scope begin genblk1[91] $end
$var parameter 8 ." i $end
$upscope $end
$scope begin genblk1[92] $end
$var parameter 8 /" i $end
$upscope $end
$scope begin genblk1[93] $end
$var parameter 8 0" i $end
$upscope $end
$scope begin genblk1[94] $end
$var parameter 8 1" i $end
$upscope $end
$scope begin genblk1[95] $end
$var parameter 8 2" i $end
$upscope $end
$scope begin genblk1[96] $end
$var parameter 8 3" i $end
$upscope $end
$scope begin genblk1[97] $end
$var parameter 8 4" i $end
$upscope $end
$scope begin genblk1[98] $end
$var parameter 8 5" i $end
$upscope $end
$scope begin genblk1[99] $end
$var parameter 8 6" i $end
$upscope $end
$scope begin genblk1[100] $end
$var parameter 8 7" i $end
$upscope $end
$scope begin genblk1[101] $end
$var parameter 8 8" i $end
$upscope $end
$scope begin genblk1[102] $end
$var parameter 8 9" i $end
$upscope $end
$scope begin genblk1[103] $end
$var parameter 8 :" i $end
$upscope $end
$scope begin genblk1[104] $end
$var parameter 8 ;" i $end
$upscope $end
$scope begin genblk1[105] $end
$var parameter 8 <" i $end
$upscope $end
$scope begin genblk1[106] $end
$var parameter 8 =" i $end
$upscope $end
$scope begin genblk1[107] $end
$var parameter 8 >" i $end
$upscope $end
$scope begin genblk1[108] $end
$var parameter 8 ?" i $end
$upscope $end
$scope begin genblk1[109] $end
$var parameter 8 @" i $end
$upscope $end
$scope begin genblk1[110] $end
$var parameter 8 A" i $end
$upscope $end
$scope begin genblk1[111] $end
$var parameter 8 B" i $end
$upscope $end
$scope begin genblk1[112] $end
$var parameter 8 C" i $end
$upscope $end
$scope begin genblk1[113] $end
$var parameter 8 D" i $end
$upscope $end
$scope begin genblk1[114] $end
$var parameter 8 E" i $end
$upscope $end
$scope begin genblk1[115] $end
$var parameter 8 F" i $end
$upscope $end
$scope begin genblk1[116] $end
$var parameter 8 G" i $end
$upscope $end
$scope begin genblk1[117] $end
$var parameter 8 H" i $end
$upscope $end
$scope begin genblk1[118] $end
$var parameter 8 I" i $end
$upscope $end
$scope begin genblk1[119] $end
$var parameter 8 J" i $end
$upscope $end
$scope begin genblk1[120] $end
$var parameter 8 K" i $end
$upscope $end
$scope begin genblk1[121] $end
$var parameter 8 L" i $end
$upscope $end
$scope begin genblk1[122] $end
$var parameter 8 M" i $end
$upscope $end
$scope begin genblk1[123] $end
$var parameter 8 N" i $end
$upscope $end
$scope begin genblk1[124] $end
$var parameter 8 O" i $end
$upscope $end
$scope begin genblk1[125] $end
$var parameter 8 P" i $end
$upscope $end
$scope begin genblk1[126] $end
$var parameter 8 Q" i $end
$upscope $end
$scope begin genblk1[127] $end
$var parameter 8 R" i $end
$upscope $end
$scope begin genblk1[128] $end
$var parameter 9 S" i $end
$upscope $end
$scope begin genblk1[129] $end
$var parameter 9 T" i $end
$upscope $end
$scope begin genblk1[130] $end
$var parameter 9 U" i $end
$upscope $end
$scope begin genblk1[131] $end
$var parameter 9 V" i $end
$upscope $end
$scope begin genblk1[132] $end
$var parameter 9 W" i $end
$upscope $end
$scope begin genblk1[133] $end
$var parameter 9 X" i $end
$upscope $end
$scope begin genblk1[134] $end
$var parameter 9 Y" i $end
$upscope $end
$scope begin genblk1[135] $end
$var parameter 9 Z" i $end
$upscope $end
$scope begin genblk1[136] $end
$var parameter 9 [" i $end
$upscope $end
$scope begin genblk1[137] $end
$var parameter 9 \" i $end
$upscope $end
$scope begin genblk1[138] $end
$var parameter 9 ]" i $end
$upscope $end
$scope begin genblk1[139] $end
$var parameter 9 ^" i $end
$upscope $end
$scope begin genblk1[140] $end
$var parameter 9 _" i $end
$upscope $end
$scope begin genblk1[141] $end
$var parameter 9 `" i $end
$upscope $end
$scope begin genblk1[142] $end
$var parameter 9 a" i $end
$upscope $end
$scope begin genblk1[143] $end
$var parameter 9 b" i $end
$upscope $end
$scope begin genblk1[144] $end
$var parameter 9 c" i $end
$upscope $end
$scope begin genblk1[145] $end
$var parameter 9 d" i $end
$upscope $end
$scope begin genblk1[146] $end
$var parameter 9 e" i $end
$upscope $end
$scope begin genblk1[147] $end
$var parameter 9 f" i $end
$upscope $end
$scope begin genblk1[148] $end
$var parameter 9 g" i $end
$upscope $end
$scope begin genblk1[149] $end
$var parameter 9 h" i $end
$upscope $end
$scope begin genblk1[150] $end
$var parameter 9 i" i $end
$upscope $end
$scope begin genblk1[151] $end
$var parameter 9 j" i $end
$upscope $end
$scope begin genblk1[152] $end
$var parameter 9 k" i $end
$upscope $end
$scope begin genblk1[153] $end
$var parameter 9 l" i $end
$upscope $end
$scope begin genblk1[154] $end
$var parameter 9 m" i $end
$upscope $end
$scope begin genblk1[155] $end
$var parameter 9 n" i $end
$upscope $end
$scope begin genblk1[156] $end
$var parameter 9 o" i $end
$upscope $end
$scope begin genblk1[157] $end
$var parameter 9 p" i $end
$upscope $end
$scope begin genblk1[158] $end
$var parameter 9 q" i $end
$upscope $end
$scope begin genblk1[159] $end
$var parameter 9 r" i $end
$upscope $end
$scope begin genblk1[160] $end
$var parameter 9 s" i $end
$upscope $end
$scope begin genblk1[161] $end
$var parameter 9 t" i $end
$upscope $end
$scope begin genblk1[162] $end
$var parameter 9 u" i $end
$upscope $end
$scope begin genblk1[163] $end
$var parameter 9 v" i $end
$upscope $end
$scope begin genblk1[164] $end
$var parameter 9 w" i $end
$upscope $end
$scope begin genblk1[165] $end
$var parameter 9 x" i $end
$upscope $end
$scope begin genblk1[166] $end
$var parameter 9 y" i $end
$upscope $end
$scope begin genblk1[167] $end
$var parameter 9 z" i $end
$upscope $end
$scope begin genblk1[168] $end
$var parameter 9 {" i $end
$upscope $end
$scope begin genblk1[169] $end
$var parameter 9 |" i $end
$upscope $end
$scope begin genblk1[170] $end
$var parameter 9 }" i $end
$upscope $end
$scope begin genblk1[171] $end
$var parameter 9 ~" i $end
$upscope $end
$scope begin genblk1[172] $end
$var parameter 9 !# i $end
$upscope $end
$scope begin genblk1[173] $end
$var parameter 9 "# i $end
$upscope $end
$scope begin genblk1[174] $end
$var parameter 9 ## i $end
$upscope $end
$scope begin genblk1[175] $end
$var parameter 9 $# i $end
$upscope $end
$scope begin genblk1[176] $end
$var parameter 9 %# i $end
$upscope $end
$scope begin genblk1[177] $end
$var parameter 9 &# i $end
$upscope $end
$scope begin genblk1[178] $end
$var parameter 9 '# i $end
$upscope $end
$scope begin genblk1[179] $end
$var parameter 9 (# i $end
$upscope $end
$scope begin genblk1[180] $end
$var parameter 9 )# i $end
$upscope $end
$scope begin genblk1[181] $end
$var parameter 9 *# i $end
$upscope $end
$scope begin genblk1[182] $end
$var parameter 9 +# i $end
$upscope $end
$scope begin genblk1[183] $end
$var parameter 9 ,# i $end
$upscope $end
$scope begin genblk1[184] $end
$var parameter 9 -# i $end
$upscope $end
$scope begin genblk1[185] $end
$var parameter 9 .# i $end
$upscope $end
$scope begin genblk1[186] $end
$var parameter 9 /# i $end
$upscope $end
$scope begin genblk1[187] $end
$var parameter 9 0# i $end
$upscope $end
$scope begin genblk1[188] $end
$var parameter 9 1# i $end
$upscope $end
$scope begin genblk1[189] $end
$var parameter 9 2# i $end
$upscope $end
$scope begin genblk1[190] $end
$var parameter 9 3# i $end
$upscope $end
$scope begin genblk1[191] $end
$var parameter 9 4# i $end
$upscope $end
$scope begin genblk1[192] $end
$var parameter 9 5# i $end
$upscope $end
$scope begin genblk1[193] $end
$var parameter 9 6# i $end
$upscope $end
$scope begin genblk1[194] $end
$var parameter 9 7# i $end
$upscope $end
$scope begin genblk1[195] $end
$var parameter 9 8# i $end
$upscope $end
$scope begin genblk1[196] $end
$var parameter 9 9# i $end
$upscope $end
$scope begin genblk1[197] $end
$var parameter 9 :# i $end
$upscope $end
$scope begin genblk1[198] $end
$var parameter 9 ;# i $end
$upscope $end
$scope begin genblk1[199] $end
$var parameter 9 <# i $end
$upscope $end
$scope begin genblk1[200] $end
$var parameter 9 =# i $end
$upscope $end
$scope begin genblk1[201] $end
$var parameter 9 ># i $end
$upscope $end
$scope begin genblk1[202] $end
$var parameter 9 ?# i $end
$upscope $end
$scope begin genblk1[203] $end
$var parameter 9 @# i $end
$upscope $end
$scope begin genblk1[204] $end
$var parameter 9 A# i $end
$upscope $end
$scope begin genblk1[205] $end
$var parameter 9 B# i $end
$upscope $end
$scope begin genblk1[206] $end
$var parameter 9 C# i $end
$upscope $end
$scope begin genblk1[207] $end
$var parameter 9 D# i $end
$upscope $end
$scope begin genblk1[208] $end
$var parameter 9 E# i $end
$upscope $end
$scope begin genblk1[209] $end
$var parameter 9 F# i $end
$upscope $end
$scope begin genblk1[210] $end
$var parameter 9 G# i $end
$upscope $end
$scope begin genblk1[211] $end
$var parameter 9 H# i $end
$upscope $end
$scope begin genblk1[212] $end
$var parameter 9 I# i $end
$upscope $end
$scope begin genblk1[213] $end
$var parameter 9 J# i $end
$upscope $end
$scope begin genblk1[214] $end
$var parameter 9 K# i $end
$upscope $end
$scope begin genblk1[215] $end
$var parameter 9 L# i $end
$upscope $end
$scope begin genblk1[216] $end
$var parameter 9 M# i $end
$upscope $end
$scope begin genblk1[217] $end
$var parameter 9 N# i $end
$upscope $end
$scope begin genblk1[218] $end
$var parameter 9 O# i $end
$upscope $end
$scope begin genblk1[219] $end
$var parameter 9 P# i $end
$upscope $end
$scope begin genblk1[220] $end
$var parameter 9 Q# i $end
$upscope $end
$scope begin genblk1[221] $end
$var parameter 9 R# i $end
$upscope $end
$scope begin genblk1[222] $end
$var parameter 9 S# i $end
$upscope $end
$scope begin genblk1[223] $end
$var parameter 9 T# i $end
$upscope $end
$scope begin genblk1[224] $end
$var parameter 9 U# i $end
$upscope $end
$scope begin genblk1[225] $end
$var parameter 9 V# i $end
$upscope $end
$scope begin genblk1[226] $end
$var parameter 9 W# i $end
$upscope $end
$scope begin genblk1[227] $end
$var parameter 9 X# i $end
$upscope $end
$scope begin genblk1[228] $end
$var parameter 9 Y# i $end
$upscope $end
$scope begin genblk1[229] $end
$var parameter 9 Z# i $end
$upscope $end
$scope begin genblk1[230] $end
$var parameter 9 [# i $end
$upscope $end
$scope begin genblk1[231] $end
$var parameter 9 \# i $end
$upscope $end
$scope begin genblk1[232] $end
$var parameter 9 ]# i $end
$upscope $end
$scope begin genblk1[233] $end
$var parameter 9 ^# i $end
$upscope $end
$scope begin genblk1[234] $end
$var parameter 9 _# i $end
$upscope $end
$scope begin genblk1[235] $end
$var parameter 9 `# i $end
$upscope $end
$scope begin genblk1[236] $end
$var parameter 9 a# i $end
$upscope $end
$scope begin genblk1[237] $end
$var parameter 9 b# i $end
$upscope $end
$scope begin genblk1[238] $end
$var parameter 9 c# i $end
$upscope $end
$scope begin genblk1[239] $end
$var parameter 9 d# i $end
$upscope $end
$scope begin genblk1[240] $end
$var parameter 9 e# i $end
$upscope $end
$scope begin genblk1[241] $end
$var parameter 9 f# i $end
$upscope $end
$scope begin genblk1[242] $end
$var parameter 9 g# i $end
$upscope $end
$scope begin genblk1[243] $end
$var parameter 9 h# i $end
$upscope $end
$scope begin genblk1[244] $end
$var parameter 9 i# i $end
$upscope $end
$scope begin genblk1[245] $end
$var parameter 9 j# i $end
$upscope $end
$scope begin genblk1[246] $end
$var parameter 9 k# i $end
$upscope $end
$scope begin genblk1[247] $end
$var parameter 9 l# i $end
$upscope $end
$scope begin genblk1[248] $end
$var parameter 9 m# i $end
$upscope $end
$scope begin genblk1[249] $end
$var parameter 9 n# i $end
$upscope $end
$scope begin genblk1[250] $end
$var parameter 9 o# i $end
$upscope $end
$scope begin genblk1[251] $end
$var parameter 9 p# i $end
$upscope $end
$scope begin genblk1[252] $end
$var parameter 9 q# i $end
$upscope $end
$scope begin genblk1[253] $end
$var parameter 9 r# i $end
$upscope $end
$scope begin genblk1[254] $end
$var parameter 9 s# i $end
$upscope $end
$scope begin genblk1[255] $end
$var parameter 9 t# i $end
$upscope $end
$upscope $end
$upscope $end
$enddefinitions $end
$comment Show the parameter values. $end
$dumpall
b11111111 t#
b11111110 s#
b11111101 r#
b11111100 q#
b11111011 p#
b11111010 o#
b11111001 n#
b11111000 m#
b11110111 l#
b11110110 k#
b11110101 j#
b11110100 i#
b11110011 h#
b11110010 g#
b11110001 f#
b11110000 e#
b11101111 d#
b11101110 c#
b11101101 b#
b11101100 a#
b11101011 `#
b11101010 _#
b11101001 ^#
b11101000 ]#
b11100111 \#
b11100110 [#
b11100101 Z#
b11100100 Y#
b11100011 X#
b11100010 W#
b11100001 V#
b11100000 U#
b11011111 T#
b11011110 S#
b11011101 R#
b11011100 Q#
b11011011 P#
b11011010 O#
b11011001 N#
b11011000 M#
b11010111 L#
b11010110 K#
b11010101 J#
b11010100 I#
b11010011 H#
b11010010 G#
b11010001 F#
b11010000 E#
b11001111 D#
b11001110 C#
b11001101 B#
b11001100 A#
b11001011 @#
b11001010 ?#
b11001001 >#
b11001000 =#
b11000111 <#
b11000110 ;#
b11000101 :#
b11000100 9#
b11000011 8#
b11000010 7#
b11000001 6#
b11000000 5#
b10111111 4#
b10111110 3#
b10111101 2#
b10111100 1#
b10111011 0#
b10111010 /#
b10111001 .#
b10111000 -#
b10110111 ,#
b10110110 +#
b10110101 *#
b10110100 )#
b10110011 (#
b10110010 '#
b10110001 &#
b10110000 %#
b10101111 $#
b10101110 ##
b10101101 "#
b10101100 !#
b10101011 ~"
b10101010 }"
b10101001 |"
b10101000 {"
b10100111 z"
b10100110 y"
b10100101 x"
b10100100 w"
b10100011 v"
b10100010 u"
b10100001 t"
b10100000 s"
b10011111 r"
b10011110 q"
b10011101 p"
b10011100 o"
b10011011 n"
b10011010 m"
b10011001 l"
b10011000 k"
b10010111 j"
b10010110 i"
b10010101 h"
b10010100 g"
b10010011 f"
b10010010 e"
b10010001 d"
b10010000 c"
b10001111 b"
b10001110 a"
b10001101 `"
b10001100 _"
b10001011 ^"
b10001010 ]"
b10001001 \"
b10001000 ["
b10000111 Z"
b10000110 Y"
b10000101 X"
b10000100 W"
b10000011 V"
b10000010 U"
b10000001 T"
b10000000 S"
b1111111 R"
b1111110 Q"
b1111101 P"
b1111100 O"
b1111011 N"
b1111010 M"
b1111001 L"
b1111000 K"
b1110111 J"
b1110110 I"
b1110101 H"
b1110100 G"
b1110011 F"
b1110010 E"
b1110001 D"
b1110000 C"
b1101111 B"
b1101110 A"
b1101101 @"
b1101100 ?"
b1101011 >"
b1101010 ="
b1101001 <"
b1101000 ;"
b1100111 :"
b1100110 9"
b1100101 8"
b1100100 7"
b1100011 6"
b1100010 5"
b1100001 4"
b1100000 3"
b1011111 2"
b1011110 1"
b1011101 0"
b1011100 /"
b1011011 ."
b1011010 -"
b1011001 ,"
b1011000 +"
b1010111 *"
b1010110 )"
b1010101 ("
b1010100 '"
b1010011 &"
b1010010 %"
b1010001 $"
b1010000 #"
b1001111 ""
b1001110 !"
b1001101 ~
b1001100 }
b1001011 |
b1001010 {
b1001001 z
b1001000 y
b1000111 x
b1000110 w
b1000101 v
b1000100 u
b1000011 t
b1000010 s
b1000001 r
b1000000 q
b111111 p
b111110 o
b111101 n
b111100 m
b111011 l
b111010 k
b111001 j
b111000 i
b110111 h
b110110 g
b110101 f
b110100 e
b110011 d
b110010 c
b110001 b
b110000 a
b101111 `
b101110 _
b101101 ^
b101100 ]
b101011 \
b101010 [
b101001 Z
b101000 Y
b100111 X
b100110 W
b100101 V
b100100 U
b100011 T
b100010 S
b100001 R
b100000 Q
b11111 P
b11110 O
b11101 N
b11100 M
b11011 L
b11010 K
b11001 J
b11000 I
b10111 H
b10110 G
b10101 F
b10100 E
b10011 D
b10010 C
b10001 B
b10000 A
b1111 @
b1110 ?
b1101 >
b1100 =
b1011 <
b1010 ;
b1001 :
b1000 9
b111 8
b110 7
b101 6
b100 5
b11 4
b10 3
b1 2
b0 1
b111 +
b0 *
$end
#0
$dumpvars
b1000 0
b11110011 /
b111 .
b11111111 -
b0 ,
b0 )
b0 (
b0 '
b0 &
1%
b0 $
1#
0"
0!
$end
#5
0#
#10
1#
#15
0#
#20
1#
#25
0#
#30
1#
#35
0#
#40
1#
#45
0#
#50
1#
#55
0#
#60
1#
#65
0#
#70
1#
#75
0#
#80
1#
#85
0#
#90
1#
#95
0#
#100
1#
1!
#105
0#
#110
1#
#115
0#
#120
1"
1#
0%
#125
0#
#130
b11111100 )
b1 &
b100100 $
b100100 '
1#
#135
0#
#140
b11111100 (
b11111100 ,
b1110100 )
b10 &
b10000001 $
b10000001 '
1#
#145
0#
#150
b1110100 (
b1110100 ,
b1110100 )
b11 &
b1001 $
b1001 '
1#
#155
0#
#160
b1100101 )
b100 &
b1100011 $
b1100011 '
1#
#165
0#
#170
b1100101 (
b1100101 ,
b11111 )
b101 &
b1101 $
b1101 '
1#
#175
0#
#180
b11111 (
b11111 ,
b11110111 )
b110 &
b10001101 $
b10001101 '
1#
#185
0#
#190
b11110111 (
b11110111 ,
b11110111 )
b111 &
b1100101 $
b1100101 '
1#
#195
0#
#200
0"
1#
#205
0#
#210
1#
#215
0#
#220
1#
#225
0#
#230
1#
#235
0#
#240
1#
#245
0#
#250
1#
#255
0#
#260
1#
#265
0#
#270
1#
#275
0#
#280
1#
#285
0#
#290
1#
#295
0#
#300
1#
#305
0#
#310
1#
#315
0#
#320
1#
#325
0#
#330
1#
#335
0#
#340
1#
#345
0#
#350
1#
#355
0#
#360
1#
#365
0#
#370
1#
#375
0#
#380
1#
#385
0#
#390
1#
#395
0#
#400
b0 )
1%
1#
b0 &
#405
0#
#410
b0 (
b0 ,
b0 )
0%
1#
#415
0#
#420
b11111100 )
b1 &
1"
b100100 $
b100100 '
1#
#425
0#
#430
b11111100 (
b11111100 ,
b1110100 )
b10 &
b10000001 $
b10000001 '
1#
#435
0#
#440
b1110100 (
b1110100 ,
b1110100 )
b11 &
b1001 $
b1001 '
1#
#445
0#
#450
b1100101 )
b100 &
b1100011 $
b1100011 '
1#
#455
0#
#460
b1100101 (
b1100101 ,
b11111 )
b101 &
b1101 $
b1101 '
1#
#465
0#
#470
b11111 (
b11111 ,
b11110111 )
b110 &
b10001101 $
b10001101 '
1#
#475
0#
#480
b11110111 (
b11110111 ,
b11110111 )
b111 &
b1100101 $
b1100101 '
1#
#485
0#
#490
b0 )
b1000 &
b11110111 $
b11110111 '
1#
#495
0#
#500
b0 (
b0 ,
b0 )
0"
1#
